pyroids/__init__.py
pyroids/_version.py
pyroids/configuration.py
pyroids/game.py
pyroids/game_objects.py
pyroids/labels.py
pyroids/play.py
pyroids/config/__init__.py
pyroids/config/expert.py
pyroids/config/novice.py
pyroids/config/template.py
pyroids/resources/README.md
pyroids/resources/bullet.png
pyroids/resources/bullet_high_velocity.png
pyroids/resources/bullet_high_velocity_red.png
pyroids/resources/explosion.png
pyroids/resources/firework.png
pyroids/resources/flame.png
pyroids/resources/mine.png
pyroids/resources/mr_bullet.wav
pyroids/resources/mr_firework.wav
pyroids/resources/mr_hvbullet.wav
pyroids/resources/mr_minelaid.wav
pyroids/resources/mr_no_stock_cannon-old1.wav
pyroids/resources/mr_no_stock_cannon.wav
pyroids/resources/mr_no_stock_fireworks.wav
pyroids/resources/mr_no_stock_hvc.wav
pyroids/resources/mr_no_stock_mines.wav
pyroids/resources/mr_no_stock_shields.wav
pyroids/resources/mr_no_stock_sld.wav
pyroids/resources/mr_radiation_warning.wav
pyroids/resources/mr_resupply.wav
pyroids/resources/mr_shieldsup.wav
pyroids/resources/mr_superdefence.wav
pyroids/resources/mr_too_much_radiation.wav
pyroids/resources/nn_bullet.wav
pyroids/resources/nn_explosion.wav
pyroids/resources/nn_firework.wav
pyroids/resources/nn_hvbullet.wav
pyroids/resources/nn_minelaid.wav
pyroids/resources/nn_no_stock_cannon.wav
pyroids/resources/nn_no_stock_fireworks.wav
pyroids/resources/nn_no_stock_hvc.wav
pyroids/resources/nn_no_stock_mines.wav
pyroids/resources/nn_no_stock_shields.wav
pyroids/resources/nn_no_stock_sld.wav
pyroids/resources/nn_radiation_warning.wav
pyroids/resources/nn_resupply.wav
pyroids/resources/nn_shieldsup.wav
pyroids/resources/nn_superlaserdefence.wav
pyroids/resources/nn_too_much_radiation.wav
pyroids/resources/pickup_blue.png
pyroids/resources/pickup_red.png
pyroids/resources/pyroid.png
pyroids/resources/rad_gauge_l2r_0.png
pyroids/resources/rad_gauge_l2r_1.png
pyroids/resources/rad_gauge_l2r_2.png
pyroids/resources/rad_gauge_l2r_3.png
pyroids-0.10.3.dist-info/licenses/LICENSE.txt
pyroids-0.10.3.dist-info/METADATA
pyroids-0.10.3.dist-info/WHEEL
pyroids-0.10.3.dist-info/entry_points.txt
pyroids-0.10.3.dist-info/top_level.txt
pyroids-0.10.3.dist-info/RECORD
