Metadata-Version: 2.4
Name: pyroids
Version: 0.10.3
Summary: Asteroids game
Author: Marcus Read
Author-email: marcusaread.prog@proton.me
License-Expression: MIT
Project-URL: homepage, https://github.com/maread99/pyroids
Project-URL: documentation, https://github.com/maread99/pyroids/blob/master/README.md
Project-URL: Issue Tracker, https://github.com/maread99/pyroids/issues
Project-URL: Source Code, https://github.com/maread99/pyroids
Keywords: game,arcade,asteroids,multiplayer,pyglet
Classifier: Development Status :: 4 - Beta
Classifier: Natural Language :: English
Classifier: Operating System :: OS Independent
Classifier: Programming Language :: Python
Classifier: Programming Language :: Python :: 3
Classifier: Programming Language :: Python :: 3.9
Classifier: Programming Language :: Python :: 3.10
Classifier: Programming Language :: Python :: 3.11
Classifier: Programming Language :: Python :: 3.12
Classifier: Programming Language :: Python :: 3.13
Classifier: Programming Language :: Python :: Implementation :: CPython
Classifier: Topic :: Games/Entertainment :: Arcade
Requires-Python: >=3.9.0
License-File: LICENSE.txt
Requires-Dist: pyglet~=1.5
Dynamic: license-file
